laserforce/__init__.py
laserforce/helpers.py
laserforce/request.py
laserforce_py-2.0.0.dist-info/licenses/LICENSE
laserforce_py-2.0.0.dist-info/METADATA
laserforce_py-2.0.0.dist-info/WHEEL
laserforce_py-2.0.0.dist-info/top_level.txt
laserforce_py-2.0.0.dist-info/RECORD
