Metadata-Version: 2.4
Name: laserforce.py
Version: 2.0.0
Summary: Python package for laserforce.
Author: spookybear0
Author-email: collinmcarroll@gmail.com
License-File: LICENSE
Dynamic: author
Dynamic: author-email
Dynamic: description
Dynamic: license-file
Dynamic: summary
